[
  {
    "equipmentPhoto" : "img/equipmentImg/cuillereCafe.jpg"
  },
  {
    "equipmentPhoto" : "img/equipmentImg/cuillereSoupe.jpg"
  },
  {
    "equipmentPhoto" : "img/equipmentImg/couteau.jpg"
  },
  {
    "equipmentPhoto" : "img/equipmentImg/fourchette.jpg"
  },
  {
    "equipmentPhoto" : "img/equipmentImg/louche.jpg"
  },
  {
    "equipmentPhoto" : "img/equipmentImg/spatule.jpg"
  },
  {
    "equipmentPhoto" : "img/equipmentImg/casserole.jpg"
  },
  {
    "equipmentPhoto" : "img/equipmentImg/poele.jpg"
  },
  {
    "equipmentPhoto" : "img/equipmentImg/econome.jpg"
  },
  {
    "equipmentPhoto" : "img/equipmentImg/plancheDecouper.jpg"
  },
  {
    "equipmentPhoto" : "img/equipmentImg/ciseaux.jpg"
  },
  {
    "equipmentPhoto" : "img/equipmentImg/rape.jpg"
  },
  {
    "equipmentPhoto" : "img/equipmentImg/fouet.jpg"
  },
  {
    "equipmentPhoto" : "img/equipmentImg/blender.jpg"
  },
  {
    "equipmentPhoto" : "img/equipmentImg/four.jpg"
  },
  {
    "equipmentPhoto" : "img/equipmentImg/pelleTarte.jpg"
  },
  {
    "equipmentPhoto" : "img/equipmentImg/passoire.jpg"
  },
  {
    "equipmentPhoto" : "img/equipmentImg/saladier.jpg"
  },
  {
    "equipmentPhoto" : "img/equipmentImg/verreDoseur.jpg"
  },
  {
    "equipmentPhoto" : "img/equipmentImg/balance.jpg"
  },
  {
    "equipmentPhoto" : "img/equipmentImg/rouleau.jpg"
  },
  {
    "equipmentPhoto" : "img/equipmentImg/mouleTarte.jpg"
  },
  {
    "equipmentPhoto" : "img/equipmentImg/gaufre.jpg"
  },
  {
    "equipmentPhoto" : "img/equipmentImg/emportePiece.jpg"
  },
  {
    "equipmentPhoto" : "img/equipmentImg/presseAgrume.jpg"
  },
  {
    "equipmentPhoto" : "img/equipmentImg/casseNoix.jpg"
  },
  {
    "equipmentPhoto" : "img/equipmentImg/decapsuleur.jpg"
  },
  {
    "equipmentPhoto" : "img/equipmentImg/tourtière.jpg"
  },
  {
    "equipmentPhoto" : "img/equipmentImg/essoreuse.jpg"
  },
  {
    "equipmentPhoto" : "img/equipmentImg/pocheDouille.jpg"
  },
  {
    "equipmentPhoto" : "img/equipmentImg/cocotte.jpg"
  },
  {
    "equipmentPhoto" : "img/equipmentImg/couvercle.jpg"
  },
  {
    "equipmentPhoto" : "img/equipmentImg/mijoteuse.jpg"
  },
  {
    "equipmentPhoto" : "img/equipmentImg/cuillereBois.jpg"
  },
  {
    "equipmentPhoto" : "img/equipmentImg/pinceau.jpg"
  },
  {
    "equipmentPhoto" : "img/equipmentImg/fondueAp.jpg"
  },
  {
    "equipmentPhoto" : "img/equipmentImg/bbq.jpg"
  },
  {
    "equipmentPhoto" : "img/equipmentImg/papierSu.jpg"
  },
  {
    "equipmentPhoto" : "img/equipmentImg/wok.jpg"
  },
  {
    "equipmentPhoto" : "img/equipmentImg/aluminium.jpg"
  },
  {
    "equipmentPhoto" : "img/equipmentImg/microOndes.jpg"
  },
  {
    "equipmentPhoto" : "img/equipmentImg/entonnoir.jpg"
  },
  {
    "equipmentPhoto" : "img/equipmentImg/grillePat.jpg"
  },
  {
    "equipmentPhoto" : "img/equipmentImg/denoyauteur.jpg"
  }

]